{
  "version": "V2-Security",
  "network": "baseSepolia",
  "chainId": 84532,
  "contracts": {
    "token": "0x6E1a42496F19173FA8081598e6a312A7ED56FEc2",
    "game": "0x9CA0B4e427Fd4A79B510a4A5542c804046210F36"
  },
  "wallets": {
    "deployer": "0xc47D6AB841F2B6b15F843BC860b32692F4103A2F",
    "oracle": "0xc47D6AB841F2B6b15F843BC860b32692F4103A2F",
    "marketing": "0xc47D6AB841F2B6b15F843BC860b32692F4103A2F",
    "liquidity": "0xc47D6AB841F2B6b15F843BC860b32692F4103A2F"
  },
  "fees": {
    "tokenTax": "3% (1% burn + 1% marketing + 1% liquidity)",
    "gameFee": "5% (3% owner + 2% burn)"
  },
  "security": [
    "Users can always withdraw",
    "Emergency withdraw bypasses pause",
    "Owner cannot access user funds",
    "Reentrancy protection",
    "Events for all actions",
    "24h oracle change timelock",
    "60s oracle cooldown between actions",
    "Bet verification on payout",
    "Payout limit per round"
  ],
  "deployedAt": "2025-12-25T04:13:53.159Z"
}